python_utilities/__init__.py
python_utilities/R/__init__.py
python_utilities/R/rserve_helper.py
python_utilities/analysis/__init__.py
python_utilities/analysis/statistics/__init__.py
python_utilities/analysis/statistics/confusion_matrix_helper.py
python_utilities/analysis/statistics/stats_helper.py
python_utilities/analysis/statistics/tests.py
python_utilities/bagit/__init__.py
python_utilities/bagit/bagit_python.py
python_utilities/beautiful_soup/__init__.py
python_utilities/beautiful_soup/beautiful_soup_helper.py
python_utilities/booleans/__init__.py
python_utilities/booleans/boolean_helper.py
python_utilities/database/MySQLdb_helper.py
python_utilities/database/PyMySQL_helper.py
python_utilities/database/__init__.py
python_utilities/database/database_helper.py
python_utilities/database/database_helper_factory.py
python_utilities/database/psycopg2_helper.py
python_utilities/dictionaries/__init__.py
python_utilities/dictionaries/dict_helper.py
python_utilities/django_utils/__init__.py
python_utilities/django_utils/django_ajax_selects_lookup_helper.py
python_utilities/django_utils/django_autocomplete_light_helper.py
python_utilities/django_utils/django_form_helper.py
python_utilities/django_utils/django_init-example.py
python_utilities/django_utils/django_memory_helper.py
python_utilities/django_utils/django_model_helper.py
python_utilities/django_utils/django_string_helper.py
python_utilities/django_utils/django_test_case_helper.py
python_utilities/django_utils/django_view_helper.py
python_utilities/django_utils/query_filter.py
python_utilities/django_utils/queryset_helper.py
python_utilities/email/__init__.py
python_utilities/email/email_helper.py
python_utilities/email/email_test.py
python_utilities/etl/__init__.py
python_utilities/etl/etl_attribute.py
python_utilities/etl/etl_django_model_loader.py
python_utilities/etl/etl_entity.py
python_utilities/etl/etl_error.py
python_utilities/etl/etl_from_dictionary.py
python_utilities/etl/etl_from_excel_with_headers.py
python_utilities_jsm-1.1.3.dist-info/LICENSE
python_utilities_jsm-1.1.3.dist-info/METADATA
python_utilities_jsm-1.1.3.dist-info/WHEEL
python_utilities_jsm-1.1.3.dist-info/top_level.txt
python_utilities_jsm-1.1.3.dist-info/RECORD
