Metadata-Version: 2.1
Name: python-utilities-jsm
Version: 1.1.3
Summary: Myriad python utilities.
Home-page: https://github.com/jonathanmorgan/python_utilities
Author: Jonathan Morgan
Author-email: jonathan.morgan.007@gmail.com
License: UNKNOWN
Platform: UNKNOWN
Classifier: Programming Language :: Python :: 3
Classifier: License :: OSI Approved :: GNU Lesser General Public License v3 or later (LGPLv3+)
Classifier: Operating System :: OS Independent
Classifier: Development Status :: 5 - Production/Stable
Classifier: Framework :: Django
Classifier: Framework :: Jupyter
Classifier: Intended Audience :: Developers
Classifier: Intended Audience :: Science/Research
Classifier: Topic :: Database :: Database Engines/Servers
Classifier: Topic :: Text Processing
Classifier: Topic :: Text Processing :: Markup :: HTML
Classifier: Topic :: Utilities
Requires-Python: >=3.6
License-File: LICENSE
Requires-Dist: bagit
Requires-Dist: beautifulsoup4
Requires-Dist: bleach
Requires-Dist: cchardet
Requires-Dist: chardet
Requires-Dist: ipykernel
Requires-Dist: openpyxl
Requires-Dist: regex
Requires-Dist: requests
Requires-Dist: six
Requires-Dist: w3lib
